gen_ai/__init__.py
gen_ai/check_pipeline.py
gen_ai/cli.py
gen_ai/constants.py
gen_ai/copy_resources.py
gen_ai/create_tables.py
gen_ai/customer.py
gen_ai/gradio_app.py
gen_ai/llm.py
platform_gen_ai-0.1.1.dist-info/LICENSE
platform_gen_ai-0.1.1.dist-info/METADATA
platform_gen_ai-0.1.1.dist-info/WHEEL
platform_gen_ai-0.1.1.dist-info/entry_points.txt
platform_gen_ai-0.1.1.dist-info/top_level.txt
platform_gen_ai-0.1.1.dist-info/RECORD
